model_profiler/__init__.py
model_profiler/profiler.py
model_profiler/utils.py
model_profiler-1.1.8.dist-info/METADATA
model_profiler-1.1.8.dist-info/WHEEL
model_profiler-1.1.8.dist-info/top_level.txt
model_profiler-1.1.8.dist-info/RECORD
