Metadata-Version: 2.1
Name: model-profiler
Version: 1.1.8
Summary: Tensorflow/Keras Model Profiler: Tells you model's memory requirement, no. of parameters, flops etc.
Home-page: https://github.com/Mr-TalhaIlyas/Tensorflow-Keras-Model-Profiler
Author: Talha Ilyas
Author-email: mr.talhailyas@gmail.com
License: UNKNOWN
Keywords: python,model_profile,gpu memory usage,model flops,model parameters,gpu availabilitymdoel memory requirement,weights memory requirement
Platform: UNKNOWN
Classifier: Intended Audience :: Education
Classifier: Programming Language :: Python :: 3
Classifier: License :: OSI Approved :: MIT License
Classifier: Operating System :: OS Independent
Requires-Dist: numpy
Requires-Dist: tabulate
